ssl_metrics_github_issue_spoilage/__init__.py
ssl_metrics_github_issue_spoilage/args.py
ssl_metrics_github_issue_spoilage/graph.py
ssl_metrics_github_issue_spoilage/main.py
ssl_metrics_github_issue_spoilage/version.py
ssl_metrics_github_issue_spoilage-0.2.dist-info/LICENSE
ssl_metrics_github_issue_spoilage-0.2.dist-info/METADATA
ssl_metrics_github_issue_spoilage-0.2.dist-info/WHEEL
ssl_metrics_github_issue_spoilage-0.2.dist-info/entry_points.txt
ssl_metrics_github_issue_spoilage-0.2.dist-info/top_level.txt
ssl_metrics_github_issue_spoilage-0.2.dist-info/RECORD
