Metadata-Version: 2.1
Name: ssl-metrics-github-issue-spoilage
Version: 0.2
Summary: SSL Metrics - GitHub Issues Analysis
Home-page: https://ssl.cs.luc.edu/projects/metricsDashboard
Author: Software and Systems Laboratory - Loyola University Chicago
Author-email: ssl-metrics@ssl.luc.edu
License: Apache License 2.0
Project-URL: Bug Tracker, https://github.com/SoftwareSystemsLaboratory/ssl-metrics-github-issue-spoilage/issues
Project-URL: GitHub Repository, https://github.com/SoftwareSystemsLaboratory/ssl-metrics-github-issue-spoilage
Keywords: git,github,software engineering,metrics,software systems laboratory,ssl,loyola,loyola university chicago,luc
Platform: UNKNOWN
Requires-Python: >=3.9
License-File: LICENSE
Requires-Dist: intervaltree (>=3.1.0)
Requires-Dist: numpy (>1.21.2)
Requires-Dist: matplotlib (>=3.4.3)
Requires-Dist: pandas (>=1.3.3)
Requires-Dist: progress (>=1.6)
Requires-Dist: python-dateutil (>=2.8.2)
Requires-Dist: requests (>=2.26.0)
